dcgoss/__init__.py
dcgoss/__main__.py
dcgoss/dcgoss.py
dcgoss/docker.py
dcgoss/docker_compose.py
dcgoss/external_command.py
dcgoss-0.1.4.dist-info/LICENSE
dcgoss-0.1.4.dist-info/METADATA
dcgoss-0.1.4.dist-info/WHEEL
dcgoss-0.1.4.dist-info/entry_points.txt
dcgoss-0.1.4.dist-info/top_level.txt
dcgoss-0.1.4.dist-info/RECORD
