Metadata-Version: 2.1
Name: dcgoss
Version: 0.1.4
Summary: A Python implementation of dcgoss
Home-page: https://github.com/shelbyallenfranks/dcgoss
Author: Shelby Allen-Franks
Author-email: shelby.allen@me.com
License: Apache License 2.0
Platform: UNKNOWN
Classifier: License :: OSI Approved :: Apache Software License
Classifier: Programming Language :: Python :: 3
Classifier: Programming Language :: Python :: 3.6
Classifier: Topic :: Software Development :: Testing
Requires-Python: >=3.6
Requires-Dist: python-dateutil (~=2.8.0)
Requires-Dist: colorama (<1.0,>=0.4) ; sys_platform == "win32"
